midoTrim/__init__.py
midoTrim/frozen.py
midoTrim/parser.py
midoTrim/ports.py
midoTrim/sockets.py
midoTrim/syx.py
midoTrim/tokenizer.py
midoTrim/version.py
midoTrim/backends/__init__.py
midoTrim/backends/_parser_queue.py
midoTrim/backends/amidi.py
midoTrim/backends/backend.py
midoTrim/backends/portmidi.py
midoTrim/backends/portmidi_init.py
midoTrim/backends/pygame.py
midoTrim/backends/rtmidi.py
midoTrim/backends/rtmidi_python.py
midoTrim/backends/rtmidi_utils.py
midoTrim/messages/__init__.py
midoTrim/messages/checks.py
midoTrim/messages/decode.py
midoTrim/messages/encode.py
midoTrim/messages/messages.py
midoTrim/messages/specs.py
midoTrim/messages/strings.py
midoTrim/midifiles/__init__.py
midoTrim/midifiles/meta.py
midoTrim/midifiles/midifiles.py
midoTrim/midifiles/tracks.py
midoTrim/midifiles/units.py
scripts/__init__.py
scripts/mido_connect.py
scripts/mido_play.py
scripts/mido_ports.py
scripts/mido_serve.py
midoTrim-1.2.10.dist-info/LICENSE
midoTrim-1.2.10.dist-info/METADATA
midoTrim-1.2.10.dist-info/WHEEL
midoTrim-1.2.10.dist-info/top_level.txt
midoTrim-1.2.10.dist-info/RECORD
