Metadata-Version: 2.1
Name: midoTrim
Version: 1.2.10
Summary: Python的mid对象处理
Home-page: https://github.com/TriM-Organization/mido
Author: Ole Martin Bjørndalen, bgArray
Author-email: TriM-Organization@hotmail.com
Classifier: Intended Audience :: Developers
Classifier: Natural Language :: Chinese (Simplified)
Classifier: License :: OSI Approved :: Apache Software License
Classifier: Operating System :: OS Independent
Classifier: Topic :: Software Development :: Libraries
Classifier: Programming Language :: Python
Classifier: Programming Language :: Python :: 3
Classifier: Programming Language :: Python :: 3.6
Classifier: Programming Language :: Python :: 3.7
Classifier: Programming Language :: Python :: 3.8
Classifier: Programming Language :: Python :: 3.9
Classifier: Programming Language :: Python :: 3.10
License-File: LICENSE
